{
    "Acceleration": [
        0.0,
        0.0
    ],
    "GuageSpeed" : 2,
    "Color": [
        1.0,
        1.0,
        1.0,
        1.0
    ],
    "DiffuseTextureIndex": 9,
    "Duration": 0.0,
    "EventRenderPass": 1,
    "MaskTextureIndex": -1,
    "MinColor": [
        1.0,
        1.0,
        1.0,
        1.0
    ],
    "Speed": [
        0.0,
        0.0
    ],
    "localMatrix": [
        80.0,
        0.0,
        0.0,
        0.0,
        0.0,
        80.0,
        0.0,
        0.0,
        0.0,
        0.0,
        1.0,
        0.0,
        37.0,
        43.0,
        0.0,
        1.0
    ],
    "renderPass": 6
}